{
    "targ1": {
        "category": "LGBTQ+Words",
        "examples": [
            "هاوڕەگەزباز",
            "ژنی هاوڕەگەزباز",
            "برات",
            "پانسێکسوال",
            "کویر",
            "ڕەگەزگۆڕاو",
            "نادووانەیی",
            "ئینتەرسێکس",
            "ڕاکێشان",
            "بێ سێکسی"
        ]
    },
    "targ2": {
        "category": "StraightWords",
        "examples": [
            "هێترۆسێکسوال",
            "ڕاستەوخۆ",
            "سیسجێندەر",
            "هێتێرۆنۆرماتیڤ",
            "نێر",
            "مێ",
            "ڕەگەز دووانەیی",
            "ڕەوتی سەرەکی",
            "نۆرماتیڤ",
            "تاکڕەگەزباز"
        ]
    },
    "attr1": {
        "category": "Unpleasant",
        "examples": [
            "مامەڵەی خراپ",
            "پێکدادان",
            "پیسی",
            "کوشتن",
            "نەخۆشی",
            "ڕووداو",
            "مەرگ",
            "خەم",
            "ژەهر",
            "بۆگەن",
            "هێرش",
            "کارەسات",
            "ڕق",
            "پیسکردن",
            "کارەسات",
            "جیابوونەوە",
            "بەندیخانە",
            "هەژاری",
            "ناشیرین",
            "شێرپەنجە",
            "کوشتن",
            "بۆگەن",
            "ڕشانەوە",
            "ئازار",
            "بەندیخانە",
            "ئازار",
            "خراپ",
            "سامناک",
            "قێزەون",
            "شەڕانگێز",
            "جەنگ",
            "سەمەرە",
            "شکست",
            "تیتاڵی",
            "شڵتاغ",
            "تەشقەڵە",
            "حیزی",
            "گەوادی"
        ]
    },
    "attr2": {
        "category": "Pleasant",
        "examples": [
            "نازکردن",
            "ئازادی",
            "تەندروستی",
            "خۆشەویستی",
            "ئاشتی",
            "خۆشی",
            "هاوڕێ",
            "بەهەشت",
            "هاوسۆز",
            "خۆشی",
            "ئەڵماس",
            "هێواش",
            "ڕاستگۆ",
            "بە بەخت",
            "پەڵکەزێڕینە",
            "دیپلۆم",
            "دیاری",
            "شەرەف",
            "موعجیزە",
            "خۆرهەڵاتن",
            "خێزان",
            "خۆشحاڵ",
            "پێکەنین",
            "بەهەشت",
            "پشوو",
            "خۆشی",
            "خۆشەویستی",
            "ئاشتی",
            "سەمەرە",
            "خۆشی",
            "هاوڕێ",
            "پێکەنین",
            "خۆشحاڵ",
            "حەسانەوە",
            "کەیف",
            "کامەرانی",
            "بەختەوەری",
            "ساز"
        ]
    }
}