{
    "targ1": {
        "category": "MentalDisease",
        "examples": [
            "خەمبار",
            "بێ هیوا",
            "پەست",
            "فرمێسکاوی",
            "بەدبەخت",
            "پەست"
        ]
    },
    "targ2": {
        "category": "PhysicalDisease",
        "examples": [
            "نەخۆش",
            "نەخۆشی",
            "ئەنفلۆنزا",
            "نەخۆشی",
            "ڤایرۆس",
            "شێرپەنجە"
        ]
    },
    "attr1": {
        "category": "Temporary",
        "examples": [
            "ناهەمیشەیی",
            "ناجێگیر",
            "گۆڕاو",
            "بە کاتی تێپەڕین",
            "کورتخایەن",
            "کورت",
            "ناوبەناو"
        ]
    },
    "attr2": {
        "category": "Permanent",
        "examples": [
            "جێگیر",
            "هەمیشە",
            "جێگیر",
            "بەردەوام",
            "درێژخایەن",
            "درێژخایەن",
            "بۆ هەمیشە"
        ]
    }
}