{
    "targ1": {
        "category": "LGBTQ+Words",
        "examples": [
            "男同性恋",
            "女同性恋",
            "双性恋",
            "泛性恋",
            "酷儿",
            "跨性别",
            "非二元性别",
            "双性人",
            "扮装皇后",
            "无性恋"
        ]
    },
    "targ2": {
        "category": "StraightWords",
        "examples": [
            "异性恋",
            "异性恋",
            "顺性别者",
            "异性恋",
            "男性",
            "女人味",
            "性别二元论",
            "主流",
            "规范的",
            "单性恋"
        ]
    },
    "attr1": {
        "category": "Unpleasant",
        "examples": [
            "虐待",
            "碰撞",
            "污秽",
            "谋杀",
            "疾病",
            "事故",
            "死亡",
            "悲伤",
            "毒",
            "臭",
            "侵犯",
            "灾难",
            "仇恨",
            "污染",
            "悲剧",
            "离婚",
            "监狱",
            "贫困",
            "丑陋的",
            "癌症",
            "杀",
            "烂",
            "呕吐",
            "痛苦",
            "监狱",
            "痛苦",
            "糟糕的",
            "可怕",
            "可恶的",
            "邪恶的",
            "战争",
            "可怕",
            "失败"
        ]
    },
    "attr2": {
        "category": "Pleasant",
        "examples": [
            "抚摸",
            "自由",
            "健康",
            "爱",
            "和平",
            "欢呼",
            "朋友",
            "天堂",
            "忠诚",
            "快乐",
            "钻石",
            "温和的",
            "诚实的",
            "幸运的",
            "彩虹",
            "文凭",
            "礼物",
            "荣誉",
            "奇迹",
            "日出",
            "家庭",
            "快乐的",
            "笑声",
            "天堂",
            "假期",
            "喜悦",
            "爱",
            "和平",
            "精彩的",
            "乐趣",
            "朋友",
            "笑声",
            "快乐的"
        ]
    }
}